pywpevent/__init__.py
pywpevent/events.py
pywpevent/main.py
pywpevent/singleton.py
pywpevent-0.1.8.dist-info/METADATA
pywpevent-0.1.8.dist-info/RECORD
pywpevent-0.1.8.dist-info/WHEEL
pywpevent-0.1.8.dist-info/top_level.txt
