Metadata-Version: 2.1
Name: pywpevent
Version: 0.1.8
Summary: Simple event management like wordpress
Home-page: https://github.com/praiwann/pywpevent
Author: Praiwan N.
Author-email: npraiwan@outlook.com
License: UNKNOWN
Keywords: wordpress,event,action,filter
Platform: UNKNOWN
Classifier: Development Status :: 4 - Beta
Classifier: License :: OSI Approved :: Apache Software License
Classifier: Programming Language :: Python :: 3
